biprop/__init__.py
biprop/biprop.py
biprop-1.0.4.dist-info/METADATA
biprop-1.0.4.dist-info/WHEEL
biprop-1.0.4.dist-info/licenses/COPYING.txt
biprop-1.0.4.dist-info/RECORD
