Metadata-Version: 2.4
Name: biprop
Version: 1.0.4
Summary: Python library for biproportional and other apportionment methods.
Project-URL: Homepage, https://github.com/herold-t/biprop
Project-URL: Issues, https://github.com/herold-t/biprop/issues
Author: Talin Herold
License-Expression: GPL-3.0-or-later
License-File: COPYING.txt
Keywords: apportionment,biproportional,elections,politics,pukelsheim
Classifier: Development Status :: 3 - Alpha
Classifier: Operating System :: OS Independent
Classifier: Programming Language :: Python :: 3
Requires-Python: >=3.7
Requires-Dist: numpy>=1.17.0
Requires-Dist: pandas>=0.23.2
